Workbook

Sheet Bank Statement 
A1: Transaction ID | B1: Date | C1: Description | D1: Reference | E1: Debit | F1: Credit
A2: B001 | B2: 46266 | C2: Customer Receipt | D2: INV1001 | E2: 0 | F2: 50000
A3: B002 | B3: 46267 | C3: Rent Payment | D3: RENT0901 | E3: 20000 | F3: 0
A4: B003 | B4: 46268 | C4: Bank Charges | D4: CHG0901 | E4: 500 | F4: 0
A5: B004 | B5: 46269 | C5: Customer Receipt | D5: INV1002 | E5: 0 | F5: 75000
A6: B005 | B6: 46270 | C6: Office Supplies | D6: OFF0901 | E6: 8500 | F6: 0
A7: B006 | B7: 46271 | C7: Customer Receipt | D7: INV1003 | E7: 0 | F7: 42000
A8: B007 | B8: 46272 | C8: Utility Payment | D8: UTIL0901 | E8: 6500 | F8: 0
A9: B008 | B9: 46273 | C9: Customer Receipt | D9: INV1004 | E9: 0 | F9: 62000
A10: B009 | B10: 46274 | C10: Bank Charges | D10: CHG0902 | E10: 750 | F10: 0
A11: B010 | B11: 46275 | C11: Insurance Payment | D11: INS0901 | E11: 12000 | F11: 0
A12: B011 | B12: 46276 | C12: Customer Receipt | D12: INV1005 | E12: 0 | F12: 38000
A13: B012 | B13: 46277 | C13: Supplier Payment | D13: SUP0901 | E13: 15500 | F13: 0
... A16: B015 | B16: 46280 | C16: Customer Receipt | D16: INV1007 | E16: 0 | F16: 47000

Sheet General Ledger
A1: GL ID | B1: Date | C1: Account | D1: Description | E1: Reference | F1: Amount
A2: GL001 | B2: 46266 | C2: Accounts Receivable | D2: Customer Receipt | E2: INV1001 | F2: 50000
A3: GL002 | B3: 46267 | C3: Rent Expense | D3: Rent Payment | E3: RENT0901 | F3: 20000
A4: GL003 | B4: 46269 | C4: Accounts Receivable | D4: Customer Receipt | E4: INV1002 | F4: 75000
A5: GL004 | B5: 46270 | C5: Office Supplies | D5: Office Supplies | E5: OFF0901 | F5: 8500
A6: GL005 | B6: 46271 | C6: Accounts Receivable | D6: Customer Receipt | E6: INV1003 | F6: 42000
A7: GL006 | B7: 46272 | C7: Utilities | D7: Utility Payment | E7: UTIL0901 | F7: 6500
A8: GL007 | B8: 46273 | C8: Accounts Receivable | D8: Customer Receipt | E8: INV1004 | F8: 60000
A9: GL008 | B9: 46275 | C9: Insurance Expense | D9: Insurance Payment | E9: INS0901 | F9: 12000
A10: GL009 | B10: 46276 | C10: Accounts Receivable | D10: Customer Receipt | E10: INV1005 | F10: 38000
A11: GL010 | B11: 46277 | C11: Accounts Payable | D11: Supplier Payment | E11: SUP0901 | F11: 15500
A12: GL011 | B12: 46278 | C12: Accounts Receivable | D12: Customer Receipt | E12: INV1006 | F12: 91000
A13: GL012 | B13: 46279 | C13: Payroll Expense | D13: Payroll Payment | E13: PAY0901 | F13: 28000
... A15: GL014 | B15: 46281 | C15: Professional Fees | D15: Consulting Payment | E15: CONS0901 | F15: 10000

Sheet BankData
A1: Transaction ID | B1: Date | C1: Description | D1: Bank Reference | E1: Debit | F1: Credit | G1: Bank Amount | H1: GL ID | I1: Account | J1: GL Reference | K1: Amount | L1: Difference | M1: Exception Type
A2: B001 | B2: 46266 | C2: Customer Receipt | D2: INV1001 | E2: 0 | F2: 50000 | G2: 50000 | H2: GL001 | I2: Accounts Receivable | J2: INV1001 | K2: 50000 | L2: 0 | M2: Matched
A3: B002 | B3: 46267 | C3: Rent Payment | D3: RENT0901 | E3: 20000 | F3: 0 | G3: 20000 | H3: GL002 | I3: Rent Expense | J3: RENT0901 | K3: 20000 | L3: 0 | M3: Matched
A4: B003 | B4: 46268 | C4: Bank Charges | D4: CHG0901 | E4: 500 | F4: 0 | G4: 500 | L4: 500 | M4: Amount Mismatch
A5: B004 | B5: 46269 | C5: Customer Receipt | D5: INV1002 | E5: 0 | F5: 75000 | G5: 75000 | H5: GL003 | I5: Accounts Receivable | J5: INV1002 | K5: 75000 | L5: 0 | M5: Matched
A6: B005 | B6: 46270 | C6: Office Supplies | D6: OFF0901 | E6: 8500 | F6: 0 | G6: 8500 | H6: GL004 | I6: Office Supplies | J6: OFF0901 | K6: 8500 | L6: 0 | M6: Matched
A7: B006 | B7: 46271 | C7: Customer Receipt | D7: INV1003 | E7: 0 | F7: 42000 | G7: 42000 | H7: GL005 | I7: Accounts Receivable | J7: INV1003 | K7: 42000 | L7: 0 | M7: Matched
A8: B007 | B8: 46272 | C8: Utility Payment | D8: UTIL0901 | E8: 6500 | F8: 0 | G8: 6500 | H8: GL006 | I8: Utilities | J8: UTIL0901 | K8: 6500 | L8: 0 | M8: Matched
A9: B008 | B9: 46273 | C9: Customer Receipt | D9: INV1004 | E9: 0 | F9: 62000 | G9: 62000 | H9: GL007 | I9: Accounts Receivable | J9: INV1004 | K9: 60000 | L9: 2000 | M9: Amount Mismatch
A10: B010 | B10: 46275 | C10: Insurance Payment | D10: INS0901 | E10: 12000 | F10: 0 | G10: 12000 | H10: GL008 | I10: Insurance Expense | J10: INS0901 | K10: 12000 | L10: 0 | M10: Matched
A11: B009 | B11: 46274 | C11: Bank Charges | D11: CHG0902 | E11: 750 | F11: 0 | G11: 750 | L11: 750 | M11: Amount Mismatch
A12: B011 | B12: 46276 | C12: Customer Receipt | D12: INV1005 | E12: 0 | F12: 38000 | G12: 38000 | H12: GL009 | I12: Accounts Receivable | J12: INV1005 | K12: 38000 | L12: 0 | M12: Matched
A13: B012 | B13: 46277 | C13: Supplier Payment | D13: SUP0901 | E13: 15500 | F13: 0 | G13: 15500 | H13: GL010 | I13: Accounts Payable | J13: SUP0901 | K13: 15500 | L13: 0 | M13: Matched
A14: B013 | B14: 46278 | C14: Customer Receipt | D14: INV1006 | E14: 0 | F14: 91000 | G14: 91000 | H14: GL011 | I14: Accounts Receivable | J14: INV1006 | K14: 91000 | L14: 0 | M14: Matched
A15: B014 | B15: 46279 | C15: Payroll Payment | D15: PAY0901 | E15: 28000 | F15: 0 | G15: 28000 | H15: GL012 | I15: Payroll Expense | J15: PAY0901 | K15: 28000 | L15: 0 | M15: Matched
A16: B015 | B16: 46280 | C16: Customer Receipt | D16: INV1007 | E16: 0 | F16: 47000 | G16: 47000 | H16: GL013 | I16: Accounts Receivable | J16: INV1007 | K16: 47000 | L16: 0 | M16: Matched
H17: GL014 | I17: Professional Fees | J17: CONS0901 | K17: 10000 | L17: -10000 | M17: Amount Mismatch
A19: Note: Consolidated view — columns A–G are Bank Statement transactions; columns H–M are the matched General Ledger entries and reconciliation exception status.

Sheet GLData
A1: GL ID | B1: Date | C1: Account | D1: Description | E1: Reference | F1: Amount
A2: GL001 | B2: 46266 | C2: Accounts Receivable | D2: Customer Receipt | E2: INV1001 | F2: 50000
A3: GL002 | B3: 46267 | C3: Rent Expense | D3: Rent Payment | E3: RENT0901 | F3: 20000
A4: GL003 | B4: 46269 | C4: Accounts Receivable | D4: Customer Receipt | E4: INV1002 | F4: 75000
A5: GL004 | B5: 46270 | C5: Office Supplies | D5: Office Supplies | E5: OFF0901 | F5: 8500
A6: GL005 | B6: 46271 | C6: Accounts Receivable | D6: Customer Receipt | E6: INV1003 | F6: 42000
A7: GL006 | B7: 46272 | C7: Utilities | D7: Utility Payment | E7: UTIL0901 | F7: 6500
A8: GL007 | B8: 46273 | C8: Accounts Receivable | D8: Customer Receipt | E8: INV1004 | F8: 60000
A9: GL008 | B9: 46275 | C9: Insurance Expense | D9: Insurance Payment | E9: INS0901 | F9: 12000
A10: GL009 | B10: 46276 | C10: Accounts Receivable | D10: Customer Receipt | E10: INV1005 | F10: 38000
A11: GL010 | B11: 46277 | C11: Accounts Payable | D11: Supplier Payment | E11: SUP0901 | F11: 15500
A12: GL011 | B12: 46278 | C12: Accounts Receivable | D12: Customer Receipt | E12: INV1006 | F12: 91000
A13: GL012 | B13: 46279 | C13: Payroll Expense | D13: Payroll Payment | E13: PAY0901 | F13: 28000
... A15: GL014 | B15: 46281 | C15: Professional Fees | D15: Consulting Payment | E15: CONS0901 | F15: 10000

Sheet Reconciliation
A1: Reference | B1: Bank Account | C1: GL Amount | D1: Difference | E1: Status | F1: Exception type | G1: Description
A2: INV1001 | B2: =SUMIF('Bank Statement '!D:D,A2,'Bank Statement '!F:F)+SUMIF('Bank Statement '!D:D,A2,'Bank Statement '!E:E) -> 50000 | C2: =SUMIF('General Ledger'!E:E,A2, 'General Ledger'!F:F) -> 50000 | D2: =B2-C2 -> 0 | E2: =IF(D2=0,"Matched","Exception") -> Matched | F2: =IF(B2=0,"GL Only",IF(C2=0,"Bank Only",IF(B2<>C2,"Amount Mismatch",""))) | G2: =IFERROR(INDEX('Bank Statement '!C:C,MATCH(A2,'Bank Statement '!D:D,0)),IFERROR(INDEX('General Ledger'!D:D,MATCH(A2,'General Ledger'!E:E,0)),"")) -> Customer Receipt
A3: RENT0901 | B3: =SUMIF('Bank Statement '!D:D,A3,'Bank Statement '!F:F)+SUMIF('Bank Statement '!D:D,A3,'Bank Statement '!E:E) -> 20000 | C3: =SUMIF('General Ledger'!E:E,A3, 'General Ledger'!F:F) -> 20000 | D3: =B3-C3 -> 0 | E3: =IF(D3=0,"Matched","Exception") -> Matched | F3: =IF(B3=0,"GL Only",IF(C3=0,"Bank Only",IF(B3<>C3,"Amount Mismatch",""))) | G3: =IFERROR(INDEX('Bank Statement '!C:C,MATCH(A3,'Bank Statement '!D:D,0)),IFERROR(INDEX('General Ledger'!D:D,MATCH(A3,'General Ledger'!E:E,0)),"")) -> Rent Payment
A4: CHG0901 | B4: =SUMIF('Bank Statement '!D:D,A4,'Bank Statement '!F:F)+SUMIF('Bank Statement '!D:D,A4,'Bank Statement '!E:E) -> 500 | C4: =SUMIF('General Ledger'!E:E,A4, 'General Ledger'!F:F) -> 0 | D4: =B4-C4 -> 500 | E4: =IF(D4=0,"Matched","Exception") -> Exception | F4: =IF(B4=0,"GL Only",IF(C4=0,"Bank Only",IF(B4<>C4,"Amount Mismatch",""))) -> Bank Only | G4: =IFERROR(INDEX('Bank Statement '!C:C,MATCH(A4,'Bank Statement '!D:D,0)),IFERROR(INDEX('General Ledger'!D:D,MATCH(A4,'General Ledger'!E:E,0)),"")) -> Bank Charges
A5: INV1002 | B5: =SUMIF('Bank Statement '!D:D,A5,'Bank Statement '!F:F)+SUMIF('Bank Statement '!D:D,A5,'Bank Statement '!E:E) -> 75000 | C5: =SUMIF('General Ledger'!E:E,A5, 'General Ledger'!F:F) -> 75000 | D5: =B5-C5 -> 0 | E5: =IF(D5=0,"Matched","Exception") -> Matched | F5: =IF(B5=0,"GL Only",IF(C5=0,"Bank Only",IF(B5<>C5,"Amount Mismatch",""))) | G5: =IFERROR(INDEX('Bank Statement '!C:C,MATCH(A5,'Bank Statement '!D:D,0)),IFERROR(INDEX('General Ledger'!D:D,MATCH(A5,'General Ledger'!E:E,0)),"")) -> Customer Receipt
A6: OFF0901 | B6: =SUMIF('Bank Statement '!D:D,A6,'Bank Statement '!F:F)+SUMIF('Bank Statement '!D:D,A6,'Bank Statement '!E:E) -> 8500 | C6: =SUMIF('General Ledger'!E:E,A6, 'General Ledger'!F:F) -> 8500 | D6: =B6-C6 -> 0 | E6: =IF(D6=0,"Matched","Exception") -> Matched | F6: =IF(B6=0,"GL Only",IF(C6=0,"Bank Only",IF(B6<>C6,"Amount Mismatch",""))) | G6: =IFERROR(INDEX('Bank Statement '!C:C,MATCH(A6,'Bank Statement '!D:D,0)),IFERROR(INDEX('General Ledger'!D:D,MATCH(A6,'General Ledger'!E:E,0)),"")) -> Office Supplies
A7: INV1003 | B7: =SUMIF('Bank Statement '!D:D,A7,'Bank Statement '!F:F)+SUMIF('Bank Statement '!D:D,A7,'Bank Statement '!E:E) -> 42000 | C7: =SUMIF('General Ledger'!E:E,A7, 'General Ledger'!F:F) -> 42000 | D7: =B7-C7 -> 0 | E7: =IF(D7=0,"Matched","Exception") -> Matched | F7: =IF(B7=0,"GL Only",IF(C7=0,"Bank Only",IF(B7<>C7,"Amount Mismatch",""))) | G7: =IFERROR(INDEX('Bank Statement '!C:C,MATCH(A7,'Bank Statement '!D:D,0)),IFERROR(INDEX('General Ledger'!D:D,MATCH(A7,'General Ledger'!E:E,0)),"")) -> Customer Receipt
A8: UTIL0901 | B8: =SUMIF('Bank Statement '!D:D,A8,'Bank Statement '!F:F)+SUMIF('Bank Statement '!D:D,A8,'Bank Statement '!E:E) -> 6500 | C8: =SUMIF('General Ledger'!E:E,A8, 'General Ledger'!F:F) -> 6500 | D8: =B8-C8 -> 0 | E8: =IF(D8=0,"Matched","Exception") -> Matched | F8: =IF(B8=0,"GL Only",IF(C8=0,"Bank Only",IF(B8<>C8,"Amount Mismatch",""))) | G8: =IFERROR(INDEX('Bank Statement '!C:C,MATCH(A8,'Bank Statement '!D:D,0)),IFERROR(INDEX('General Ledger'!D:D,MATCH(A8,'General Ledger'!E:E,0)),"")) -> Utility Payment
A9: INV1004 | B9: =SUMIF('Bank Statement '!D:D,A9,'Bank Statement '!F:F)+SUMIF('Bank Statement '!D:D,A9,'Bank Statement '!E:E) -> 62000 | C9: =SUMIF('General Ledger'!E:E,A9, 'General Ledger'!F:F) -> 60000 | D9: =B9-C9 -> 2000 | E9: =IF(D9=0,"Matched","Exception") -> Exception | F9: =IF(B9=0,"GL Only",IF(C9=0,"Bank Only",IF(B9<>C9,"Amount Mismatch",""))) -> Amount Mismatch | G9: =IFERROR(INDEX('Bank Statement '!C:C,MATCH(A9,'Bank Statement '!D:D,0)),IFERROR(INDEX('General Ledger'!D:D,MATCH(A9,'General Ledger'!E:E,0)),"")) -> Customer Receipt
A10: CHG0902 | B10: =SUMIF('Bank Statement '!D:D,A10,'Bank Statement '!F:F)+SUMIF('Bank Statement '!D:D,A10,'Bank Statement '!E:E) -> 750 | C10: =SUMIF('General Ledger'!E:E,A10, 'General Ledger'!F:F) -> 0 | D10: =B10-C10 -> 750 | E10: =IF(D10=0,"Matched","Exception") -> Exception | F10: =IF(B10=0,"GL Only",IF(C10=0,"Bank Only",IF(B10<>C10,"Amount Mismatch",""))) -> Bank Only | G10: =IFERROR(INDEX('Bank Statement '!C:C,MATCH(A10,'Bank Statement '!D:D,0)),IFERROR(INDEX('General Ledger'!D:D,MATCH(A10,'General Ledger'!E:E,0)),"")) -> Bank Charges
A11: INS0901 | B11: =SUMIF('Bank Statement '!D:D,A11,'Bank Statement '!F:F)+SUMIF('Bank Statement '!D:D,A11,'Bank Statement '!E:E) -> 12000 | C11: =SUMIF('General Ledger'!E:E,A11, 'General Ledger'!F:F) -> 12000 | D11: =B11-C11 -> 0 | E11: =IF(D11=0,"Matched","Exception") -> Matched | F11: =IF(B11=0,"GL Only",IF(C11=0,"Bank Only",IF(B11<>C11,"Amount Mismatch",""))) | G11: =IFERROR(INDEX('Bank Statement '!C:C,MATCH(A11,'Bank Statement '!D:D,0)),IFERROR(INDEX('General Ledger'!D:D,MATCH(A11,'General Ledger'!E:E,0)),"")) -> Insurance Payment
A12: INV1005 | B12: =SUMIF('Bank Statement '!D:D,A12,'Bank Statement '!F:F)+SUMIF('Bank Statement '!D:D,A12,'Bank Statement '!E:E) -> 38000 | C12: =SUMIF('General Ledger'!E:E,A12, 'General Ledger'!F:F) -> 38000 | D12: =B12-C12 -> 0 | E12: =IF(D12=0,"Matched","Exception") -> Matched | F12: =IF(B12=0,"GL Only",IF(C12=0,"Bank Only",IF(B12<>C12,"Amount Mismatch",""))) | G12: =IFERROR(INDEX('Bank Statement '!C:C,MATCH(A12,'Bank Statement '!D:D,0)),IFERROR(INDEX('General Ledger'!D:D,MATCH(A12,'General Ledger'!E:E,0)),"")) -> Customer Receipt
A13: SUP0901 | B13: =SUMIF('Bank Statement '!D:D,A13,'Bank Statement '!F:F)+SUMIF('Bank Statement '!D:D,A13,'Bank Statement '!E:E) -> 15500 | C13: =SUMIF('General Ledger'!E:E,A13, 'General Ledger'!F:F) -> 15500 | D13: =B13-C13 -> 0 | E13: =IF(D13=0,"Matched","Exception") -> Matched | F13: =IF(B13=0,"GL Only",IF(C13=0,"Bank Only",IF(B13<>C13,"Amount Mismatch",""))) | G13: =IFERROR(INDEX('Bank Statement '!C:C,MATCH(A13,'Bank Statement '!D:D,0)),IFERROR(INDEX('General Ledger'!D:D,MATCH(A13,'General Ledger'!E:E,0)),"")) -> Supplier Payment
... A16: INV1007 | B16: =SUMIF('Bank Statement '!D:D,A16,'Bank Statement '!F:F)+SUMIF('Bank Statement '!D:D,A16,'Bank Statement '!E:E) -> 47000 | C16: =SUMIF('General Ledger'!E:E,A16, 'General Ledger'!F:F) -> 47000 | D16: =B16-C16 -> 0 | E16: =IF(D16=0,"Matched","Exception") -> Matched | F16: =IF(B16=0,"GL Only",IF(C16=0,"Bank Only",IF(B16<>C16,"Amount Mismatch",""))) | G16: =IFERROR(INDEX('Bank Statement '!C:C,MATCH(A16,'Bank Statement '!D:D,0)),IFERROR(INDEX('General Ledger'!D:D,MATCH(A16,'General Ledger'!E:E,0)),"")) -> Customer Receipt
A17: CONS0901 | B17: 0 | C17: 10000 | D17: =B17-C17 -> -10000 | E17: =IF(D17=0,"Matched","Exception") -> Exception | F17: =IF(B17=0,"GL Only",IF(C17=0,"Bank Only",IF(B17<>C17,"Amount Mismatch",""))) -> GL Only | G17: =IFERROR(INDEX('Bank Statement '!C:C,MATCH(A17,'Bank Statement '!D:D,0)),IFERROR(INDEX('General Ledger'!D:D,MATCH(A17,'General Ledger'!E:E,0)),"")) -> Consulting Payment

Sheet Exceptions
A1: Reference | B1: Bank Amount | C1: GL Amount | D1: Differenence | E1: Exception Type | F1: Description | G1: Investigation/Action
A2: CHG0901 | B2: =INDEX(Reconciliation!B:B,MATCH(A2,Reconciliation!A:A,0)) -> 500 | C2: =INDEX(Reconciliation!C:C,MATCH(A2,Reconciliation!A:A,0)) -> 0 | D2: =INDEX(Reconciliation!D:D,MATCH(A2,Reconciliation!A:A,0)) -> 500 | E2: =INDEX(Reconciliation!F:F,MATCH(A2,Reconciliation!A:A,0)) -> Bank Only | F2: =INDEX(Reconciliation!G:G,MATCH(A2,Reconciliation!A:A,0)) -> Bank Charges | G2: Verify bank statement charges in the GL; obtain supporting bank advice if required
A3: INV1004 | B3: =INDEX(Reconciliation!B:B,MATCH(A3,Reconciliation!A:A,0)) -> 62000 | C3: =INDEX(Reconciliation!C:C,MATCH(A3,Reconciliation!A:A,0)) -> 60000 | D3: =INDEX(Reconciliation!D:D,MATCH(A3,Reconciliation!A:A,0)) -> 2000 | E3: =INDEX(Reconciliation!F:F,MATCH(A3,Reconciliation!A:A,0)) -> Amount Mismatch | F3: =INDEX(Reconciliation!G:G,MATCH(A3,Reconciliation!A:A,0)) -> Customer Receipt | G3: Investigate the 2000 difference against the customer receipt and supporting invoice; confirm whether the GL needs adjustment
A4: CHG0902 | B4: =INDEX(Reconciliation!B:B,MATCH(A4,Reconciliation!A:A,0)) -> 750 | C4: =INDEX(Reconciliation!C:C,MATCH(A4,Reconciliation!A:A,0)) -> 0 | D4: =INDEX(Reconciliation!D:D,MATCH(A4,Reconciliation!A:A,0)) -> 750 | E4: =INDEX(Reconciliation!F:F,MATCH(A4,Reconciliation!A:A,0)) -> Bank Only | F4: =INDEX(Reconciliation!G:G,MATCH(A4,Reconciliation!A:A,0)) -> Bank Charges | G4: Verify bank statement charge and record the missing bank charge entry in the GL
A5: CONS0901 | B5: =INDEX(Reconciliation!B:B,MATCH(A5,Reconciliation!A:A,0)) -> 0 | C5: =INDEX(Reconciliation!C:C,MATCH(A5,Reconciliation!A:A,0)) -> 10000 | D5: =INDEX(Reconciliation!D:D,MATCH(A5,Reconciliation!A:A,0)) -> -10000 | E5: =INDEX(Reconciliation!F:F,MATCH(A5,Reconciliation!A:A,0)) -> GL Only | F5: =INDEX(Reconciliation!G:G,MATCH(A5,Reconciliation!A:A,0)) -> Consulting Payment | G5: Verify the consultingpayment in supporting documents and bank statement; investigate why it is recorded in the GL but not in the bank statement

Sheet Management Summary 
A1: Month-End Reconciliation Summary
A3: Total Transactions Reviewed | B3: =COUNTA(Reconciliation!A2:A17) -> 16
A4: Matched Transactions | B4: =COUNTIF(Reconciliation!D2:D17,0) -> 12
A5: Exception Transactions | B5: =COUNTIF(Reconciliation!D2:D17,"<>0") -> 4
A6: Reconciliation Rate | B6: =B4/B3 -> 0.75
A7: Bank Only Exceptions | B7: =COUNTIFS(Reconciliation!D2:D17,">0",Reconciliation!C2:C17,0) -> 2
A8: GL Only Exceptions | B8: =COUNTIFS(Reconciliation!D2:D17,"<0",Reconciliation!B2:B17,0) -> 1
A9: Amount Mismatch Exceptions | B9: =COUNTIFS(Reconciliation!D2:D17,"<>0",Reconciliation!B2:B17,">0",Reconciliation!C2:C17,">0") -> 1
A10: Total Exception Value | B10: =SUM(Exceptions!D2:D5) -> -6750
A11: Gross Exception Value | B11: =SUMPRODUCT(ABS(Exceptions!D2:D5)) -> 13250
A12: Key Month End Observation | B12: 12 of 16 transactions were sucessfully reconciled, resulting in a 75% reconcilation rate. Four exceptions remain, with a gross exception value of 13,250. The key items requiring investigation are 10,000 GL-only Consulting Payment and the 2000 customer receipt mismatch. Bank charges totalling1250 are also pending GL recognition.
